rabbitsketch.cp37-win_amd64.pyd
rabbitsketch-0.0.3.dist-info/LICENSE.txt
rabbitsketch-0.0.3.dist-info/METADATA
rabbitsketch-0.0.3.dist-info/WHEEL
rabbitsketch-0.0.3.dist-info/top_level.txt
rabbitsketch-0.0.3.dist-info/RECORD
