Metadata-Version: 2.1
Name: rabbitsketch
Version: 0.0.3
Summary: a python package for sequence sketching
Home-page: UNKNOWN
Author: Zekun Yin
Author-email: zekun.yin@mail.sdu.edu.cn
License: UNKNOWN
Platform: UNKNOWN
